mi_band_data_extract/__init__.py
mi_band_data_extract/custom_exception.py
mi_band_data_extract/get_data.py
mi_band_data_extract/get_workout_detail.py
mi_band_data_extract/logger.py
mi_band_data_extract-0.0.6.dist-info/METADATA
mi_band_data_extract-0.0.6.dist-info/WHEEL
mi_band_data_extract-0.0.6.dist-info/top_level.txt
mi_band_data_extract-0.0.6.dist-info/RECORD
